nautobot_ssot_unifi/__init__.py
nautobot_ssot_unifi/app-config-schema.json
nautobot_ssot_unifi/const.py
nautobot_ssot_unifi/hardware_models.csv
nautobot_ssot_unifi/jobs.py
nautobot_ssot_unifi/sigals.py
nautobot_ssot_unifi/ssot/adapters.py
nautobot_ssot_unifi/ssot/models.py
nautobot_ssot_unifi/tests/__init__.py
nautobot_ssot_unifi/tests/fixtures/get_devices.json
nautobot_ssot_unifi/tests/test_basic.py
nautobot_ssot_unifi/tests/test_unifi_adapter.py
nautobot_ssot_unifi/unifi/__init__.py
nautobot_ssot_unifi/unifi/client.py
nautobot_ssot_unifi/utils/__init__.py
nautobot_ssot_unifi/utils/nautobot.py
nautobot_ssot_unifi/utils/unifi.py
nautobot_ssot_unifi-1.0.4.dist-info/LICENSE
nautobot_ssot_unifi-1.0.4.dist-info/METADATA
nautobot_ssot_unifi-1.0.4.dist-info/WHEEL
nautobot_ssot_unifi-1.0.4.dist-info/RECORD
