Metadata-Version: 2.3
Name: nautobot-ssot-unifi
Version: 1.0.4
Summary: Nautobot SSoT integration for Ubiquiti Unifi.
License: Apache-2.0
Keywords: nautobot,nautobot-app,nautobot-plugin
Author: Andrew Bates
Author-email: abates@omeganetserv.com
Requires-Python: >=3.12,<3.13
Classifier: Development Status :: 5 - Production/Stable
Classifier: Intended Audience :: Developers
Classifier: License :: OSI Approved :: Apache Software License
Classifier: Programming Language :: Python :: 3
Classifier: Programming Language :: Python :: 3.12
Classifier: Programming Language :: Python :: 3.10
Classifier: Programming Language :: Python :: 3.11
Classifier: Programming Language :: Python :: 3.8
Classifier: Programming Language :: Python :: 3.9
Provides-Extra: all
Requires-Dist: aiounifi
Requires-Dist: napalm-unifi
Requires-Dist: nautobot (>=2.3.0,<3.0.0)
Requires-Dist: nautobot-ssot (>=3.3.0,<4.0.0)
Project-URL: Documentation, https://docs.nautobot.com/projects/nautobot-ssot-unifi/en/latest/
Project-URL: Homepage, https://github.com/abates/nautobot-app-ssot-unifi
Project-URL: Repository, https://github.com/abates/nautobot-app-ssot-unifi
